coppersun_brass/__init__.py
coppersun_brass/__main__.py
coppersun_brass/config.py
coppersun_brass/main.py
coppersun_brass/runner.py
coppersun_brass/scheduler.py
coppersun_brass/agents/__init__.py
coppersun_brass/agents/base_agent.py
coppersun_brass/agents/base_agent_fixed.py
coppersun_brass/agents/planner/__init__.py
coppersun_brass/agents/planner/cycle_detection.py
coppersun_brass/agents/planner/priority_optimizer.py
coppersun_brass/agents/planner/task_generator.py
coppersun_brass/agents/scout/__init__.py
coppersun_brass/agents/scout/cli_commands.py
coppersun_brass/agents/scout/dcp_integrator.py
coppersun_brass/agents/scout/research_generator.py
coppersun_brass/agents/scout/scout_agent.py
coppersun_brass/agents/scout/test_scout_findings.json
coppersun_brass/agents/scout/todo_detector.py
coppersun_brass/agents/scout/analyzers/__init__.py
coppersun_brass/agents/scout/analyzers/base_analyzer.py
coppersun_brass/agents/scout/analyzers/evolution_tracker.py
coppersun_brass/agents/scout/analyzers/javascript_analyzer.py
coppersun_brass/agents/scout/analyzers/pattern_analyzer.py
coppersun_brass/agents/scout/analyzers/python_analyzer.py
coppersun_brass/agents/scout/analyzers/typescript_analyzer.py
coppersun_brass/agents/scout/testdata/test_basic_todos.py
coppersun_brass/agents/scout/testdata/test_researchable_todos.py
coppersun_brass/agents/strategist/__init__.py
coppersun_brass/agents/strategist/config.py
coppersun_brass/agents/strategist/duplicate_detector.py
coppersun_brass/agents/strategist/orchestration_engine.py
coppersun_brass/agents/strategist/priority_engine.py
coppersun_brass/agents/strategist/strategist_agent.py
coppersun_brass/agents/strategist/autonomous/__init__.py
coppersun_brass/agents/strategist/autonomous/capability_assessor.py
coppersun_brass/agents/strategist/autonomous/chunked_analyzer.py
coppersun_brass/agents/strategist/autonomous/context_analyzer.py
coppersun_brass/agents/strategist/autonomous/dependency_analyzer.py
coppersun_brass-2.5.8.dist-info/licenses/LICENSE
coppersun_brass-2.5.8.dist-info/METADATA
coppersun_brass-2.5.8.dist-info/WHEEL
coppersun_brass-2.5.8.dist-info/entry_points.txt
coppersun_brass-2.5.8.dist-info/top_level.txt
coppersun_brass-2.5.8.dist-info/RECORD
