Metadata-Version: 2.4
Name: coppersun-brass
Version: 2.5.8
Summary: Development Intelligence for AI Agents - Copper Sun Product Line
Home-page: https://github.com/coppersun/brass
Author: Copper Sun Team
Author-email: Copper Sun Team <brass@coppersun.com>
License: Proprietary
Project-URL: Homepage, https://github.com/coppersun/brass
Project-URL: Documentation, https://docs.brass.coppersun.dev
Project-URL: Repository, https://github.com/coppersun/brass
Project-URL: Issues, https://github.com/coppersun/brass/issues
Keywords: code-analysis,ai,ml,devops,automation,copper-sun,brass
Classifier: Development Status :: 4 - Beta
Classifier: Intended Audience :: Developers
Classifier: Topic :: Software Development :: Quality Assurance
Classifier: Topic :: Software Development :: Testing
Classifier: License :: Other/Proprietary License
Classifier: Programming Language :: Python :: 3
Classifier: Programming Language :: Python :: 3.8
Classifier: Programming Language :: Python :: 3.9
Classifier: Programming Language :: Python :: 3.10
Classifier: Programming Language :: Python :: 3.11
Classifier: Programming Language :: Python :: 3.12
Requires-Python: >=3.8
License-File: LICENSE
Requires-Dist: click>=8.0
Requires-Dist: pydantic>=2.0
Requires-Dist: aiofiles>=0.8
Requires-Dist: watchdog>=3.0.0
Requires-Dist: jsonschema>=4.0
Requires-Dist: networkx>=3.0
Requires-Dist: pyyaml>=6.0
Requires-Dist: pyperclip>=1.8
Requires-Dist: requests>=2.28
Requires-Dist: urllib3<2,>=1.26
Requires-Dist: anthropic>=0.21.3
Requires-Dist: python-dotenv>=1.0.0
Requires-Dist: apscheduler>=3.10
Requires-Dist: rich>=13.0
Requires-Dist: psutil>=5.0
Provides-Extra: ml
Provides-Extra: dev
Requires-Dist: pytest>=7.0; extra == "dev"
Requires-Dist: pytest-asyncio>=0.21; extra == "dev"
Requires-Dist: pytest-cov>=4.0; extra == "dev"
Requires-Dist: black>=23.0; extra == "dev"
Requires-Dist: mypy>=1.5; extra == "dev"
Requires-Dist: ruff>=0.1; extra == "dev"
Dynamic: author
Dynamic: home-page
Dynamic: license-file
Dynamic: requires-python
